spectral_wave_data-1.0.0rc1.data/purelib/spectral_wave_data/LICENSE.txt
spectral_wave_data-1.0.0rc1.data/purelib/spectral_wave_data/README.txt
spectral_wave_data-1.0.0rc1.data/purelib/spectral_wave_data/SWD_logo.ico
spectral_wave_data-1.0.0rc1.data/purelib/spectral_wave_data/SpectralWaveData.dll
spectral_wave_data-1.0.0rc1.data/purelib/spectral_wave_data/SpectralWaveData.exp
spectral_wave_data-1.0.0rc1.data/purelib/spectral_wave_data/SpectralWaveData.lib
spectral_wave_data-1.0.0rc1.data/purelib/spectral_wave_data/__init__.py
spectral_wave_data-1.0.0rc1.data/purelib/spectral_wave_data/kind_values.mod
spectral_wave_data-1.0.0rc1.data/purelib/spectral_wave_data/open_swd_file_def.mod
spectral_wave_data-1.0.0rc1.data/purelib/spectral_wave_data/spectral_interpolation_def.mod
spectral_wave_data-1.0.0rc1.data/purelib/spectral_wave_data/spectral_wave_data.h
spectral_wave_data-1.0.0rc1.data/purelib/spectral_wave_data/spectral_wave_data.py
spectral_wave_data-1.0.0rc1.data/purelib/spectral_wave_data/spectral_wave_data_allocate_def.mod
spectral_wave_data-1.0.0rc1.data/purelib/spectral_wave_data/spectral_wave_data_c_def.mod
spectral_wave_data-1.0.0rc1.data/purelib/spectral_wave_data/spectral_wave_data_def.mod
spectral_wave_data-1.0.0rc1.data/purelib/spectral_wave_data/spectral_wave_data_error.mod
spectral_wave_data-1.0.0rc1.data/purelib/spectral_wave_data/spectral_wave_data_shape_1_impl_1_def.mod
spectral_wave_data-1.0.0rc1.data/purelib/spectral_wave_data/spectral_wave_data_shape_2_impl_1_def.mod
spectral_wave_data-1.0.0rc1.data/purelib/spectral_wave_data/spectral_wave_data_shape_3_impl_1_def.mod
spectral_wave_data-1.0.0rc1.data/purelib/spectral_wave_data/spectral_wave_data_shape_4_impl_1_def.mod
spectral_wave_data-1.0.0rc1.data/purelib/spectral_wave_data/spectral_wave_data_shape_4_impl_2_def.mod
spectral_wave_data-1.0.0rc1.data/purelib/spectral_wave_data/spectral_wave_data_shape_5_impl_1_def.mod
spectral_wave_data-1.0.0rc1.dist-info/METADATA
spectral_wave_data-1.0.0rc1.dist-info/RECORD
spectral_wave_data-1.0.0rc1.dist-info/WHEEL
spectral_wave_data-1.0.0rc1.dist-info/entry_points.txt
spectral_wave_data-1.0.0rc1.dist-info/top_level.txt
