Metadata-Version: 2.1
Name: spectral-wave-data
Version: 1.0.0rc1
Summary: An API for ocean wave kinematics
Home-page: https://github.com/SpectralWaveData
Maintainer: Jens B. Helmers & Odin Gramstad, DNVGL
Maintainer-email: Jens.Bloch.Helmers@dnvgl.com
License: MIT license - Copyright DNVGL 2019-2020
Keywords: API ocean wave kinematics
Platform: UNKNOWN
Classifier: Development Status :: 5 - Production/Stable
Classifier: Intended Audience :: Science/Research
Classifier: Topic :: Scientific/Engineering :: Mathematics
Classifier: Topic :: Scientific/Engineering :: Physics
Classifier: License :: OSI Approved :: MIT License
Classifier: Programming Language :: Python :: 2.7
Classifier: Programming Language :: Python :: 3.5
Classifier: Programming Language :: Python :: 3.6
Classifier: Programming Language :: Python :: 3.7
Classifier: Programming Language :: Python :: 3.8
Classifier: Operating System :: Microsoft :: Windows :: Windows 10
Classifier: Operating System :: POSIX :: Linux
